odoo/addons/website_crm_quick_answer/README.rst
odoo/addons/website_crm_quick_answer/__init__.py
odoo/addons/website_crm_quick_answer/__manifest__.py
odoo/addons/website_crm_quick_answer/data/base_automation_data.xml
odoo/addons/website_crm_quick_answer/i18n/es.po
odoo/addons/website_crm_quick_answer/i18n/it.po
odoo/addons/website_crm_quick_answer/i18n/website_crm_quick_answer.pot
odoo/addons/website_crm_quick_answer/migrations/17.0.1.0.0/pre-migration.py
odoo/addons/website_crm_quick_answer/readme/CONFIGURE.md
odoo/addons/website_crm_quick_answer/readme/CONTRIBUTORS.md
odoo/addons/website_crm_quick_answer/readme/DESCRIPTION.md
odoo/addons/website_crm_quick_answer/readme/USAGE.md
odoo/addons/website_crm_quick_answer/static/description/icon.png
odoo/addons/website_crm_quick_answer/static/description/index.html
odoo_addon_website_crm_quick_answer-17.0.1.0.0.5.dist-info/METADATA
odoo_addon_website_crm_quick_answer-17.0.1.0.0.5.dist-info/WHEEL
odoo_addon_website_crm_quick_answer-17.0.1.0.0.5.dist-info/top_level.txt
odoo_addon_website_crm_quick_answer-17.0.1.0.0.5.dist-info/RECORD
